README.txt
setup.py
gstatsd/__init__.py
gstatsd/client.py
gstatsd/client_test.py
gstatsd/core.py
gstatsd/service.py
gstatsd/service_test.py
gstatsd/sink.py
gstatsd.egg-info/PKG-INFO
gstatsd.egg-info/SOURCES.txt
gstatsd.egg-info/dependency_links.txt
gstatsd.egg-info/entry_points.txt
gstatsd.egg-info/top_level.txt