Metadata-Version: 1.1
Name: gstatsd
Version: 0.5
Summary: A statsd service and client in Python + gevent
Home-page: http://github.com/phensley/gstatsd
Author: Patrick Hensley
Author-email: spaceboy@indirect.com
License: Apache 2.0
Keywords: stats,graphite,statsd,gevent
Platform: UNKNOWN
Classifier: Development Status :: 3 - Alpha
Classifier: Intended Audience :: Developers
Classifier: License :: OSI Approved :: Apache Software License
Classifier: Operating System :: MacOS :: MacOS X
Classifier: Operating System :: POSIX :: Linux
Classifier: Operating System :: Unix
Classifier: Programming Language :: Python
Classifier: Programming Language :: Python :: 2.6
Classifier: Programming Language :: Python :: 2.7
Classifier: Topic :: Software Development :: Libraries :: Python Modules
